smt_switch/__init__.py
smt_switch/smt_switch_base.cpython-310-x86_64-linux-gnu.so
smt_switch/pysmt_frontend/__init__.py
smt_switch/pysmt_frontend/pysmt_solver.py
smt_switch.libs/libgmp-d944b113.so.10.3.2
smt_switch.libs/libgmpxx-355ee5d2.so.4
smt_switch.libs/libsmt-switch-7ec74748.so
smt_switch.libs/libsmt-switch-bitwuzla-2730c392.so
smt_switch.libs/libsmt-switch-cvc5-a1c0d350.so
smt_switch.libs/libsmt-switch-z3-6862c626.so
smt_switch-0.3.2.dist-info/METADATA
smt_switch-0.3.2.dist-info/WHEEL
smt_switch-0.3.2.dist-info/top_level.txt
smt_switch-0.3.2.dist-info/RECORD
